{"code":"91.24.11","district":"Paro","city":"Kabupaten Nduga","province":"Papua","slug":"papua/kabupaten-nduga/paro","villages":[{"code":"91.24.11.2001","village":"Paro","slug":"papua/kabupaten-nduga/paro/paro"},{"code":"91.24.11.2002","village":"Lombrik","slug":"papua/kabupaten-nduga/paro/lombrik"},{"code":"91.24.11.2003","village":"Animarem","slug":"papua/kabupaten-nduga/paro/animarem"},{"code":"91.24.11.2004","village":"Tawelma","slug":"papua/kabupaten-nduga/paro/tawelma"},{"code":"91.24.11.2005","village":"Loaraba","slug":"papua/kabupaten-nduga/paro/loaraba"}]}