[{"id":"6101","nama":"Kabupaten Sambas"},{"id":"6102","nama":"Kabupaten Mempawah"},{"id":"6103","nama":"Kabupaten Sanggau"},{"id":"6104","nama":"Kabupaten Ketapang"},{"id":"6105","nama":"Kabupaten Sintang"},{"id":"6106","nama":"Kabupaten Kapuas Hulu"},{"id":"6107","nama":"Kabupaten Bengkayang"},{"id":"6108","nama":"Kabupaten Landak"},{"id":"6109","nama":"Kabupaten Sekadau"},{"id":"6110","nama":"Kabupaten Melawi"},{"id":"6111","nama":"Kabupaten Kayong Utara"},{"id":"6112","nama":"Kabupaten Kubu Raya"},{"id":"6171","nama":"Kota Pontianak"},{"id":"6172","nama":"Kota Singkawang"}]