[{"id":"3501","nama":"Kabupaten Pacitan"},{"id":"3502","nama":"Kabupaten Ponorogo"},{"id":"3503","nama":"Kabupaten Trenggalek"},{"id":"3504","nama":"Kabupaten Tulungagung"},{"id":"3505","nama":"Kabupaten Blitar"},{"id":"3506","nama":"Kabupaten Kediri"},{"id":"3507","nama":"Kabupaten Malang"},{"id":"3508","nama":"Kabupaten Lumajang"},{"id":"3509","nama":"Kabupaten Jember"},{"id":"3510","nama":"Kabupaten Banyuwangi"},{"id":"3511","nama":"Kabupaten Bondowoso"},{"id":"3512","nama":"Kabupaten Situbondo"},{"id":"3513","nama":"Kabupaten Probolinggo"},{"id":"3514","nama":"Kabupaten Pasuruan"},{"id":"3515","nama":"Kabupaten Sidoarjo"},{"id":"3516","nama":"Kabupaten Mojokerto"},{"id":"3517","nama":"Kabupaten Jombang"},{"id":"3518","nama":"Kabupaten Nganjuk"},{"id":"3519","nama":"Kabupaten Madiun"},{"id":"3520","nama":"Kabupaten Magetan"},{"id":"3521","nama":"Kabupaten Ngawi"},{"id":"3522","nama":"Kabupaten Bojonegoro"},{"id":"3523","nama":"Kabupaten Tuban"},{"id":"3524","nama":"Kabupaten Lamongan"},{"id":"3525","nama":"Kabupaten Gresik"},{"id":"3526","nama":"Kabupaten Bangkalan"},{"id":"3527","nama":"Kabupaten Sampang"},{"id":"3528","nama":"Kabupaten Pamekasan"},{"id":"3529","nama":"Kabupaten Sumenep"},{"id":"3571","nama":"Kota Kediri"},{"id":"3572","nama":"Kota Blitar"},{"id":"3573","nama":"Kota Malang"},{"id":"3574","nama":"Kota Probolinggo"},{"id":"3575","nama":"Kota Pasuruan"},{"id":"3576","nama":"Kota Mojokerto"},{"id":"3577","nama":"Kota Madiun"},{"id":"3578","nama":"Kota Surabaya"},{"id":"3579","nama":"Kota Batu"}]